Workbook
Name cnListe: [2]Sheet1!$A$1:$A$65536

Sheet Achats_LUX
B1: Carla_________ | I1: Annexe 1
B2: Dossier
B4: Address
B6: Détail de la TVA en amont sur les achats de biens et des services à Luxembourg
B11: Date | C11: Fournisseurs | D11: N° de facture | E11: Nature | F11: Montant HTVA (EUR) | G11: Taux de TVA | H11: Montant TVA (EUR) | I11: Montant TTC (EUR)
B12: 45709 | C12: Chambre des Métiers | D12: ART/2025/177747 | E12: Taxe carte d'affiliation | F12: 35 | G12: 0 | H12: =F12*G12 -> 0 | I12: =F12+H12 -> 35
B13: 45747 | C13: Action | D13: 500110190000254 | E13: Materiel | F13: 10.23 | G13: 0.17 | H13: =F13*G13 -> 1.7391 | I13: =F13+H13 -> 11.9691
B14: 45733 | C14: Action | D14: 500910190002255 | E14: Materiel | F14: 22.95 | G14: 0.17 | H14: =F14*G14 -> 3.9015 | I14: =F14+H14 -> 26.8515
B15: 45740 | C15: C&A | D15: 320041/2025/4 | E15: Vetement | F15: 29.11 | G15: 0.03 | H15: =F15*G15 -> 0.8733 | I15: =F15+H15 -> 29.9833
B16: 45721 | C16: Zeemann | D16: 50140100578850 | E16: Vetement | F16: 15.97 | G16: 0.03 | H16: =F16*G16 -> 0.4791 | I16: =F16+H16 -> 16.4491
B17: 45721 | C17: Zeemann | D17: 50140100578850 | E17: Vetement | F17: 5.13 | G17: 0.17 | H17: =F17*G17 -> 0.8721 | I17: =F17+H17 -> 6.0021
B18: 45721 | C18: Auchan Kirchberg | D18: 381_2025_38672 | E18: Ordinateur | F18: 792.71 | G18: 0.17 | H18: =F18*G18 -> 134.7607 | I18: =F18+H18 -> 927.4707
B19: 45733 | C19: Den Bastelgeck | D19: 25030078 | E19: Materiel | F19: 30.85 | G19: 0.17 | H19: =F19*G19 -> 5.2445 | I19: =F19+H19 -> 36.0945
B20: 45748 | C20: Tenue Complete | D20: #FA029457 | E20: Materiel | F20: 202.47 | G20: 0.2 | H20: =F20*G20 -> 40.494 | I20: =F20+H20 -> 242.964
B21: 45775 | C21: Batiself | D21: 250428080704 | E21: Materiel | F21: 63.63 | G21: 0.17 | H21: =F21*G21 -> 10.8171 | I21: =F21+H21 -> 74.4471
B22: 45782 | C22: Tenue Complete | D22: #FA029557 | E22: Materiel | F22: 141.09 | G22: 0.2 | H22: =F22*G22 -> 28.218 | I22: =F22+H22 -> 169.308
B23: 45826 | C23: Baumarkt Globus | D23: 31/ 2673 | E23: Materiel | F23: 11.86 | G23: 0.17 | H23: =F23*G23 -> 2.0162 | I23: =F23+H23 -> 13.8762
B24: 07/07/205 | C24: Restaurant Carpe Diem | D24: 804901 | E24: Déjeuner d'affaire | F24: 52.43 | G24: 0.03 | H24: =F24*G24 -> 1.5729 | I24: =F24+H24 -> 54.0029
B25: 45847 | C25: Hornbach | D25: 242424002811 | E25: Materiel | F25: 16.5 | G25: 0.17 | H25: =F25*G25 -> 2.805 | I25: =F25+H25 -> 19.305
B26: 45985 | C26: AVA Pommerloch | D26: 869842 | E26: Materiel | F26: 57.52 | G26: 0.17 | H26: =F26*G26 -> 9.7784 | I26: =F26+H26 -> 67.2984
B27: 45976 | C27: TEMU | D27: PO-114-173005700 | E27: Materiel | F27: 133.16 | G27: 0.17 | H27: =F27*G27 -> 22.6372 | I27: =F27+H27 -> 155.7972
B28: 46018 | C28: AVA Pommerloch | D28: 2025252007354 | E28: Materiel | F28: 48.7 | G28: 0.17 | H28: =F28*G28 -> 8.279 | I28: =F28+H28 -> 56.979
H29: =F29*G29 -> 0 | I29: =F29+H29 -> 0
H30: =F30*G30 -> 0 | I30: =F30+H30 -> 0
H31: =F31*G31 -> 0 | I31: =F31+H31 -> 0
H32: =F32*G32 -> 0 | I32: =F32+H32 -> 0
H33: =F33*G33 -> 0 | I33: =F33+H33 -> 0
H34: =F34*G34 -> 0 | I34: =F34+H34 -> 0
H35: =F35*G35 -> 0 | I35: =F35+H35 -> 0
H36: =F36*G36 -> 0 | I36: =F36+H36 -> 0
H37: =F37*G37 -> 0 | I37: =F37+H37 -> 0
H38: =F38*G38 -> 0 | I38: =F38+H38 -> 0
H39: =F39*G39 -> 0 | I39: =F39+H39 -> 0
H40: =F40*G40 -> 0 | I40: =F40+H40 -> 0
... H49: =F49*G49 -> 0 | I49: =F49+H49 -> 0
B50: Total en EUR | F50: =SUM(F12:F49) -> 1669.31 | G50: =SUM(G12:G49) -> 2.36 | H50: =SUM(H12:H49) -> 274.4881 | I50: =SUM(I12:I49) -> 1943.7981

Sheet AIC
B1: =+Achats_LUX!B1 -> Carla_________ | M1: Annexe 3
B2: Dossier
B3: 0
B4: Address
B6: Détail des acquisitions intracommunautaires de biens ou services
B11: Date | C11: Fournisseurs | D11: N° de facture | E11: Nature des biens | F11: Pays | G11: Montant HTVA (Devise) | H11: Devise | I11: Taux de change | J11: Montant HTVA (EUR) | K11: Taux TVA | L11: Montant TVA (EUR) | M11: Montant TTC (EUR)
B13: 45730 | C13: Luminol | D13: 700012591 | E13: Matériel | F13: FR | G13: 321.42 | H13: EUR | I13: 0 | J13: =G13 -> 321.42 | K13: 0 | L13: 0 | M13: =SUM(J13+L13) -> 321.42
B14: 45720 | C14: Luminol | D14: 700011600 | E14: Machine | F14: FR | G14: 6190.83 | H14: EUR | I14: 0 | J14: =G14 -> 6190.83 | K14: 0 | L14: =+K14*J14 -> 0 | M14: =SUM(J14+L14) -> 6190.83
B15: 45750 | C15: Força Temeraria LDA | D15: 3760 | E15: Materiel | F15: PT | G15: 713.91 | H15: EUR | I15: 0 | J15: =G15 -> 713.91 | K15: 0 | L15: =+K15*J15 -> 0 | M15: =SUM(J15+L15) -> 713.91
B16: 45796 | C16: Cleverbridge GmbH | D16: AKD-736118752288 | E16: Abonnement logiciel | F16: DE | G16: 235.04 | H16: EUR | I16: 0 | J16: =G16 -> 235.04 | K16: 0 | L16: =+K16*J16 -> 0 | M16: =SUM(J16+L16) -> 235.04
B17: 45819 | C17: Tenue Complete | D17: #FA029669 | E17: Materiel | F17: FR | G17: 1169.4 | H17: EUR | I17: 0 | J17: =G17 -> 1169.4 | K17: 0 | L17: =+K17*J17 -> 0 | M17: =SUM(J17+L17) -> 1169.4
B18: 45856 | C18: Printfabrik | D18: PF19320 | E18: Materiel | F18: FR | G18: 48.43 | H18: EUR | I18: 0 | J18: =G18 -> 48.43 | K18: 0 | L18: =+K18*J18 -> 0 | M18: =SUM(J18+L18) -> 48.43
B19: 45895 | C19: Plantète Gateau | D19: #FA603862 | E19: Materiel | F19: FR | G19: 631.53 | H19: EUR | I19: 0 | J19: =G19 -> 631.53 | K19: 0 | L19: =+K19*J19 -> 0 | M19: =SUM(J19+L19) -> 631.53
B20: 45901 | C20: Printfabrik | D20: PF19683 | E20: Materiel | F20: FR | G20: 41.85 | H20: EUR | I20: 0 | J20: =G20 -> 41.85 | K20: 0 | L20: =+K20*J20 -> 0 | M20: =SUM(J20+L20) -> 41.85
B21: 45904 | C21: Tenue Complete | D21: #FA029880 | E21: Materiel | F21: FR | G21: 757.21 | H21: EUR | I21: 0 | J21: =G21 -> 757.21 | K21: 0 | L21: =+K21*J21 -> 0 | M21: =SUM(J21+L21) -> 757.21
B22: 45907 | C22: Luminol | D22: 700026846 | E22: Materiel | F22: FR | G22: 166.67 | H22: EUR | I22: 0 | J22: =G22 -> 166.67 | K22: 0 | L22: =+K22*J22 -> 0 | M22: =SUM(J22+L22) -> 166.67
B23: 45908 | C23: Luminol | D23: 700034467 | E23: Materiel | F23: FR | G23: 49.83 | H23: EUR | I23: 0 | J23: =G23 -> 49.83 | K23: 0 | L23: =+K23*J23 -> 0 | M23: =SUM(J23+L23) -> 49.83
B24: 45910 | C24: Tenue Complete | D24: #FA029892 | E24: Materiel | F24: FR | G24: 54.07 | H24: EUR | I24: 0 | J24: =G24 -> 54.07 | K24: 0 | L24: =+K24*J24 -> 0 | M24: =SUM(J24+L24) -> 54.07
B25: 45930 | C25: Tenue Complete | D25: #FA029939 | E25: Materiel | F25: FR | G25: 99.58 | H25: EUR | I25: 0 | J25: =G25 -> 99.58 | K25: 0 | L25: =+K25*J25 -> 0 | M25: =SUM(J25+L25) -> 99.58
B26: 45944 | C26: Luminol | D26: 700038301-1 | E26: Machine | F26: FR | G26: 5925 | H26: EUR | I26: 0 | J26: =G26 -> 5925 | K26: 0 | L26: =+K26*J26 -> 0 | M26: =SUM(J26+L26) -> 5925
B27: 45967 | C27: Tenue Complete | D27: #FA030009 | E27: Materiel | F27: FR | G27: 367.42 | J27: =G27 -> 367.42 | K27: 0 | L27: =+K27*J27 -> 0 | M27: =SUM(J27+L27) -> 367.42
J28: =G28 -> 0 | K28: 0 | L28: =+K28*J28 -> 0 | M28: =SUM(J28+L28) -> 0
J29: =G29 -> 0 | K29: 0 | L29: =+K29*J29 -> 0 | M29: =SUM(J29+L29) -> 0
J30: =G30 -> 0 | K30: 0 | L30: =+K30*J30 -> 0 | M30: =SUM(J30+L30) -> 0
J31: =G31 -> 0 | K31: 0 | L31: =+K31*J31 -> 0 | M31: =SUM(J31+L31) -> 0
J32: =G32 -> 0 | K32: 0 | L32: =+K32*J32 -> 0 | M32: =SUM(J32+L32) -> 0
J33: =G33 -> 0 | K33: 0 | L33: =+K33*J33 -> 0 | M33: =SUM(J33+L33) -> 0
J34: =G34 -> 0 | K34: 0 | L34: =+K34*J34 -> 0 | M34: =SUM(J34+L34) -> 0
J35: =G35 -> 0 | K35: 0 | L35: =+K35*J35 -> 0 | M35: =SUM(J35+L35) -> 0
J36: =G36 -> 0 | K36: 0 | L36: =+K36*J36 -> 0 | M36: =SUM(J36+L36) -> 0
J37: =G37 -> 0 | K37: 0 | L37: =+K37*J37 -> 0 | M37: =SUM(J37+L37) -> 0
J38: =G38 -> 0 | K38: 0 | L38: =+K38*J38 -> 0 | M38: =SUM(J38+L38) -> 0
J39: =G39 -> 0 | K39: 0 | L39: =+K39*J39 -> 0 | M39: =SUM(J39+L39) -> 0
... J48: =G48 -> 0 | K48: 0 | L48: =+K48*J48 -> 0 | M48: =SUM(J48+L48) -> 0
I49: Total en EUR | J49: =SUM(J12:J48) -> 16772.19 | L49: =SUM(L12:L48) -> 0 | M49: =SUM(M12:M48) -> 16772.19

Sheet Chida_LUX
B1: =+Achats_LUX!B1 -> Carla_________ | L1: Annexe 2
B2: Dossier
B3: 0
B4: Address
O5: =500*30 -> 15000
B6: Détail du chiffre d'affaires_Chiffre d'affaires taxable réalisé à Luxembourg ( ventes)
B11: Date | C11: Clients | D11: N° facture | E11: Nature | F11: Montant HTVA (Devise) | G11: Devise | H11: Taux de change | I11: Montant HTVA (EUR) | J11: Taux TVA | K11: Montant TVA (EUR) | L11: Montant TTC (EUR)
B12: 45746 | C12: Sonia | D12: 1 | E12: Fabrication objet | F12: 153.85 | G12: EUR | H12: 0 | I12: =+F12 -> 153.85 | J12: 0.17 | K12: =+J12*I12 -> 26.1545 | L12: =+K12+I12 -> 180.0045
B13: 45746 | C13: Axel Terlicher | D13: 2 | E13: Fabrication objet | F13: 25.64 | G13: EUR | H13: 0 | I13: =+F13 -> 25.64 | J13: 0.17 | K13: =+J13*I13 -> 4.3588 | L13: =+K13+I13 -> 29.9988
B14: 45746 | C14: Doris Brito | D14: 3 | E14: Fabrication objet | F14: 33.33 | G14: EUR | H14: 0 | I14: =+F14 -> 33.33 | J14: 0.17 | K14: =+J14*I14 -> 5.6661 | L14: =+K14+I14 -> 38.9961
B15: 45759 | C15: Fernanda | D15: 4 | E15: Fabrication objet | F15: 38.46 | G15: EUR | H15: 0 | I15: =+F15 -> 38.46 | J15: 0.17 | K15: =+J15*I15 -> 6.5382 | L15: =+K15+I15 -> 44.9982
B16: 45759 | C16: Sonia | D16: 5 | E16: Fabrication objet | F16: 44.02 | G16: EUR | H16: 0 | I16: =+F16 -> 44.02 | J16: 0.17 | K16: =+J16*I16 -> 7.4834 | L16: =+K16+I16 -> 51.5034
B17: 45766 | C17: Marlene Dos Santos | D17: 6 | E17: Fabrication objet | F17: 76.92 | G17: EUR | H17: 0 | I17: =+F17 -> 76.92 | J17: 0.17 | K17: =+J17*I17 -> 13.0764 | L17: =+K17+I17 -> 89.9964
B18: 45770 | C18: Claudia | D18: 7 | E18: Fabrication objet | F18: 50 | G18: EUR | H18: 0 | I18: =+F18 -> 50 | J18: 0.17 | K18: =+J18*I18 -> 8.5 | L18: =+K18+I18 -> 58.5
B19: 45772 | C19: Maison Relais Useldange | D19: 8 | E19: Fabrication objet | F19: 194.87 | G19: EUR | H19: 0 | I19: =+F19 -> 194.87 | J19: 0.17 | K19: =+J19*I19 -> 33.1279 | L19: =+K19+I19 -> 227.9979
B20: 45778 | C20: Ana | D20: 9 | E20: Fabrication objet | F20: 119.66 | G20: EUR | H20: 0 | I20: =+F20 -> 119.66 | J20: 0.17 | K20: =+J20*I20 -> 20.3422 | L20: =+K20+I20 -> 140.0022
B21: 45803 | C21: Commune Grosbous | D21: 10 | E21: Fabrication objet | F21: 512.82 | G21: EUR | H21: 0 | I21: =+F21 -> 512.82 | J21: 0.17 | K21: =+J21*I21 -> 87.1794 | L21: =+K21+I21 -> 599.9994
B22: 45786 | C22: Coiffure Beim Anes | D22: 11 | E22: Fabrication objet | F22: 190.78 | G22: EUR | H22: 0 | I22: =+F22 -> 190.78 | J22: 0.17 | K22: =+J22*I22 -> 32.4326 | L22: =+K22+I22 -> 223.2126
B23: 45791 | C23: Sandy | D23: 12 | E23: Fabrication objet | F23: 11.11 | G23: EUR | H23: 0 | I23: =+F23 -> 11.11 | J23: 0.17 | K23: =+J23*I23 -> 1.8887 | L23: =+K23+I23 -> 12.9987
... B48: 45942 | C48: Commune Grosbous | D48: 40 | E48: Fabrication objet | F48: 29.06 | G48: EUR | H48: 0 | I48: =+F48 -> 29.06 | J48: 0.17 | K48: =+J48*I48 -> 4.9402 | L48: =+K48+I48 -> 34.0002
B49: 12/10/205 | C49: Commune Grosbous | D49: 39 | E49: Fabrication objet | F49: 26.15 | G49: EUR | H49: 0 | I49: =+F49 -> 26.15 | J49: 0.17 | K49: =+J49*I49 -> 4.4455 | L49: =+K49+I49 -> 30.5955
B50: 45945 | C50: Salon Beim Anes | D50: 41 | E50: Fabrication objet | F50: 60 | G50: EUR | H50: 0 | I50: =+F50 -> 60 | J50: 0.17 | K50: =+J50*I50 -> 10.2 | L50: =+K50+I50 -> 70.2
B51: 45946 | C51: Beim Bäcker Jos SARL | D51: 31 | E51: Fabrication objet | F51: 85 | G51: EUR | H51: 0 | I51: =+F51 -> 85 | J51: 0 | K51: =+J51*I51 -> 0 | L51: =+K51+I51 -> 85
B52: 45997 | C52: Paula Brites | D52: 42 | E52: Fabrication objet | F52: 34.19 | G52: EUR | H52: 0 | I52: =+F52 -> 34.19 | J52: 0.17 | K52: =+J52*I52 -> 5.8123 | L52: =+K52+I52 -> 40.0023
B53: 46002 | C53: Hernani Andrade Ramos | D53: 43 | E53: Fabrication objet | F53: 45.3 | G53: EUR | H53: 0 | I53: =+F53 -> 45.3 | J53: 0.17 | K53: =+J53*I53 -> 7.701 | L53: =+K53+I53 -> 53.001
B54: 46009 | C54: Pietro Scardamaglia | D54: 44 | E54: Fabrication objet | F54: 38.46 | G54: EUR | H54: 0 | I54: =+F54 -> 38.46 | J54: 0.17 | K54: =+J54*I54 -> 6.5382 | L54: =+K54+I54 -> 44.9982
B55: 46009 | C55: Ana Silva | D55: 45 | E55: Fabrication objet | F55: 34.19 | G55: EUR | H55: 0 | I55: =+F55 -> 34.19 | J55: 0.17 | K55: =+J55*I55 -> 5.8123 | L55: =+K55+I55 -> 40.0023
B56: 46009 | C56: Joffer Sandy | D56: 47 | E56: Fabrication objet | F56: 4.27 | G56: EUR | H56: 0 | I56: =+F56 -> 4.27 | J56: 0.17 | K56: =+J56*I56 -> 0.7259 | L56: =+K56+I56 -> 4.9959
B57: 46011 | C57: Ana Costa | D57: 46 | E57: Fabrication objet | F57: 34.19 | G57: EUR | H57: 0 | I57: =+F57 -> 34.19 | J57: 0.17 | K57: =+J57*I57 -> 5.8123 | L57: =+K57+I57 -> 40.0023
B58: 46014 | C58: Salon Boissenet et MM | D58: 48 | E58: Fabrication objet | F58: 480 | G58: EUR | H58: 0 | I58: =+F58 -> 480 | J58: 0.17 | K58: =+J58*I58 -> 81.6 | L58: =+K58+I58 -> 561.6
D59: 1 | E59: Fabrication objet | G59: EUR | H59: 0 | I59: =+F59 -> 0 | J59: 0.17 | K59: =+J59*I59 -> 0 | L59: =+K59+I59 -> 0
D60: 1 | E60: Fabrication objet | G60: EUR | H60: 0 | I60: =+F60 -> 0 | J60: 0.17 | K60: =+J60*I60 -> 0 | L60: =+K60+I60 -> 0
H61: Total en EUR | I61: =SUM(I13:I60) -> 6484.63 | K61: =SUM(K13:K60) -> 1087.9371 | L61: =SUM(L13:L60) -> 7572.5671
H63: Total en EUR | I63: =SUM(I13:I60) -> 6484.63 | K63: =SUM(K13:K60) -> 1087.9371 | L63: =SUM(L13:L60) -> 7572.5671

Sheet Chida_UE
B1: =+Achats_LUX!B1 -> Carla_________ | K1: Annexe 2
B2: Dossier
B3: 0
B4: Address
B6: Détail du chiffre d'affaires_Prestations de services à des identifiés à la TVA dans un autre Etat membre
B11: Prestations de services non exonérées dans l'Etat membre du preneur redevable
B13: Date | C13: Clients | D13: N° facture | E13: Nature | F13: Pays | G13: N° de TVA | H13: Montant (Devise) | I13: Devise | J13: Taux de change | K13: Montant HTVA EUR
J20: Total en EUR | K20: =SUM(K14:K16) -> 0
B24: Prestations de services exonérées dans l'Etat membre du preneur redevable
B26: Date paiement | C26: Emprunteurs | D26: Pays de l'emprunteur | E26: Nature | F26: Montant HTVA (Devise) | G26: Devise | H26: Taux de change | I26: Montant HTVA (EUR)
H30: Total en EUR

Sheet Importations 1
B1: =+Achats_LUX!B1 -> Carla_________ | M1: Annexe 5
B2: Dossier
B3: 0
B4: Address
B6: Détail des importations de biens
B11: Date | C11: Fournisseurs | D11: N° de facture | E11: Nature des biens | F11: Pays | G11: Montant HTVA (Devise) | H11: Devise | I11: Taux de change | J11: Montant HTVA (EUR) | K11: Taux TVA | L11: Montant TVA (EUR) | M11: Montant TTC (EUR)
I15: Total en EUR | J15: =SUM(J12:J13) -> 0 | L15: =SUM(L12:L13) -> 0 | M15: =SUM(M12:M13) -> 0

Sheet Chida_HUE
B1: =+Achats_LUX!B1 -> Carla_________ | J1: ="Annexe "&[3]Index!A28 -> Annexe 2
B2: Dossier
B3: 0
B4: Address
B6: Détail du chiffre d'affaires_Autres opérations réalisées à l'étranger
M8: Exportation : article 43/1/a e b)
B10: Autres opérations réalisées à l'étranger__Clients redevables situés en dehors de l'Union européenne
B12: Date | C12: Clients | D12: N°facture | E12: Nature | F12: Pays | G12: Montant HTVA (Devise) | H12: Devise | I12: Taux de change | J12: Montant HTVA (EUR)
B19: 43951 | C19: Peres Service | D19: FLU2000024 | E19: Marchandises | F19: CH | G19: 3575 | H19: EUR | I19: 1 | J19: =+I19*G19 -> 3575 | L19: ok
B20: 44008 | C20: Peres Service | D20: FLU2000045 | E20: Marchandises | F20: CH | G20: =940+20 -> 960 | H20: EUR | I20: 1 | J20: =+I20*G20 -> 960 | L20: ok
B21: 43991 | C21: Global Network Technologies sarl | D21: FLU2000038 | E21: Marchandises | F21: CH | G21: =485.46+18 -> 503.46 | H21: EUR | I21: 1 | J21: =+I21*G21 -> 503.46 | L21: ok
B22: 44001 | C22: Peres Service | D22: FLU2000041 | E22: Mses, Mod.Lam Blom-X | F22: CH | G22: =2795+100 -> 2895 | H22: EUR | I22: 1 | J22: =+I22*G22 -> 2895 | L22: ok
B24: 43879 | C24: Peres Service | D24: FLU2000009 | E24: Marchandises | F24: CH | G24: =1378-200+30 -> 1208 | H24: EUR | I24: 1 | J24: =+I24*G24 -> 1208
B25: 43901 | C25: Peres Service | D25: FLU2000017 | E25: Marchandises | F25: CH | G25: 5590 | H25: EUR | I25: 1 | J25: =+I25*G25 -> 5590
I27: Total en EUR | J27: =SUM(J13:J17) -> 0
B31: Prestations de services exonérées_Clients redevables situés en dehors de l'Union européenne
B33: Date paiement | C33: Emprunteurs | D33: Pays de l'emprunteur | E33: Nature | F33: Montant HTVA (Devise) | G33: Devise | H33: Taux de change | I33: Montant HTVA (EUR)
H37: Total en EUR
B41: Autres opérations réalisées à l'étranger__Loyers taxés à l'étranger
B43: Date | C43: Nature | D43: N°facture | E43: Pays | F43: Montant HTVA (Devise) | G43: Devise | H43: Taux de change | I43: Montant HTVA (EUR)
H47: Total en EUR

Sheet Importations
B1: =Chida_LUX!B1 -> Carla_________ | M1: Annexe 5
B2: =Chida_LUX!B2 -> Dossier
B3: =Chida_LUX!B3 -> 0
B4: =Chida_LUX!B4 -> Address
B6: Détail des importations de biens
B8: =Chida_LUX!B8 -> 0
B11: Date | C11: Fournisseurs | D11: N° de facture | E11: Nature des biens | F11: Pays | G11: Montant HTVA (Devise) | H11: Devise | I11: Taux de change | J11: Montant HTVA (EUR) | K11: Taux TVA | L11: Montant TVA (EUR) | M11: Montant TTC (EUR)
H12: EUR | I12: 1 | J12: =+G12 -> 0 | K12: 0.17 | L12: =+K12*J12 -> 0 | M12: =+J12 -> 0
I14: Total en EUR | J14: =SUM(J12:J13) -> 0 | L14: =SUM(L12:L13) -> 0 | M14: =SUM(M12:M13) -> 0

Sheet Montant TVA déductible
B1: =+Achats_LUX!B1 -> Carla_________ | G1: Annexe x
B2: Dossier
B3: 0
B4: Address
B6: Détermination du montant de la taxe en amont déductible
B8: =Chida_LUX!B8 -> 0
B11: Prorata général de déduction de l'année XXXX | D11: 1 | E11: (A)
B12: basé sur la dernière déclaration TVA annuelle déposée
F14: Base imposable HTVA | G14: Montant de TVA
B16: Calcul du montant de la taxe en amont déductible :
B18: Montant total de la taxe en amont_Biens/Services à l'intérieur du pays | E18: cf. annexe | F18: =Achats_LUX!F50 -> 1669.31 | G18: =F18*0.17 -> 283.7827
B19: Montant total de la taxe en amont sur les acquisitions intracommunautaires de biens | E19: cf. annexe | F19: =AIC!J49 -> 16772.19 | G19: =F19*0.17 -> 2851.2723
B20: Montant total de la taxe en amont sur les importations | E20: cf. annexe | F20: ='Importations 1'!J15 -> 0 | G20: =F20*0.17 -> 0
B21: Montant total de la taxe en amont_Taxe déclarée comme débiteur (art 17 § 1 b) ) | E21: cf. annexe | F21: 0 | G21: =F21*0.17 -> 0
B23: Total de la taxe en amont soumise au prorata général de déductibilité | G23: =SUM(G18:G21) -> 3135.055 | H23: (B)
B25: Total de la taxe en amont déductible suivant le prorata général de déduction | F25: (A) * (B) | G25: =G23*D11 -> 3135.055
B26: Total de la taxe en amont non déductible | G26: =G23-G25 -> 0

Sheet Feuil1
